windowtitles_translation_llm/backwardTranslation.py
windowtitles_translation_llm/config.py
windowtitles_translation_llm/constants.py
windowtitles_translation_llm/forwardTranslation.py
windowtitles_translation_llm/main.py
windowtitles_translation_llm-0.1.0.dist-info/METADATA
windowtitles_translation_llm-0.1.0.dist-info/WHEEL
windowtitles_translation_llm-0.1.0.dist-info/RECORD
