Metadata-Version: 2.3
Name: windowtitles-translation-llm
Version: 0.1.0
Summary: This project aims to forward translate and backward translate window titles using the help of llama model.
Author: qiblatainf
Author-email: qiblatain@live.com
Requires-Python: >=3.10
Classifier: Programming Language :: Python :: 3
Classifier: Programming Language :: Python :: 3.10
Classifier: Programming Language :: Python :: 3.11
Classifier: Programming Language :: Python :: 3.12
Classifier: Programming Language :: Python :: 3.13
Requires-Dist: ollama
Requires-Dist: tqdm
